Metadata-Version: 1.0
Name: PYPIPPACKAGEEXAMPLE
Version: 1.0
Summary: Paquete de prueba para una clase de Udemy
Home-page: https://github.com/Stefanoberro/pypipackageexample
Author: Stefano Berro
Author-email: UNKNOWN
License: MIT
Platform: UNKNOWN
